aws_console_url/__init__.py
aws_console_url/_version.py
aws_console_url/api.py
aws_console_url/compat.py
aws_console_url/console.py
aws_console_url/model.py
aws_console_url/utils.py
aws_console_url/docs/__init__.py
aws_console_url/srv/__init__.py
aws_console_url/srv/a2i.py
aws_console_url/srv/apigateway.py
aws_console_url/srv/athena.py
aws_console_url/srv/awslambda.py
aws_console_url/srv/batch.py
aws_console_url/srv/cloudformation.py
aws_console_url/srv/cloudwatch.py
aws_console_url/srv/codebuild.py
aws_console_url/srv/codecommit.py
aws_console_url/srv/codepipeline.py
aws_console_url/srv/dynamodb.py
aws_console_url/srv/ec2.py
aws_console_url/srv/ecr.py
aws_console_url/srv/ecs.py
aws_console_url/srv/eventbridge.py
aws_console_url/srv/glue.py
aws_console_url/srv/ground_truth.py
aws_console_url/srv/iam.py
aws_console_url/srv/kinesis.py
aws_console_url/srv/kinesis_firehose.py
aws_console_url/srv/kinesis_video.py
aws_console_url/srv/kms.py
aws_console_url/srv/rds.py
aws_console_url/srv/s3.py
aws_console_url/srv/sagemaker.py
aws_console_url/srv/secretmanager.py
aws_console_url/srv/sns.py
aws_console_url/srv/sqs.py
aws_console_url/srv/ssm.py
aws_console_url/srv/step_function.py
aws_console_url/srv/vpc.py
aws_console_url/tests/__init__.py
aws_console_url/tests/helper.py
aws_console_url/tests/paths.py
aws_console_url-1.4.1.dist-info/AUTHORS.rst
aws_console_url-1.4.1.dist-info/LICENSE.txt
aws_console_url-1.4.1.dist-info/METADATA
aws_console_url-1.4.1.dist-info/WHEEL
aws_console_url-1.4.1.dist-info/top_level.txt
aws_console_url-1.4.1.dist-info/RECORD
